{
  "db_name": "SQLite",
  "query": "\n            SELECT id, nostr_pubkey, username, password_hash, encrypted_nsec, created_at, updated_at\n            FROM users\n            WHERE nostr_pubkey = ?\n            ",
  "describe": {
    "columns": [
      {
        "name": "id",
        "ordinal": 0,
        "type_info": "Integer"
      },
      {
        "name": "nostr_pubkey",
        "ordinal": 1,
        "type_info": "Text"
      },
      {
        "name": "username",
        "ordinal": 2,
        "type_info": "Text"
      },
      {
        "name": "password_hash",
        "ordinal": 3,
        "type_info": "Text"
      },
      {
        "name": "encrypted_nsec",
        "ordinal": 4,
        "type_info": "Text"
      },
      {
        "name": "created_at",
        "ordinal": 5,
        "type_info": "Text"
      },
      {
        "name": "updated_at",
        "ordinal": 6,
        "type_info": "Text"
      }
    ],
    "parameters": {
      "Right": 1
    },
    "nullable": [
      false,
      false,
      false,
      true,
      true,
      false,
      false
    ]
  },
  "hash": "9f2b3b39e01d562a60078e4610ff1433dd42b9b591aee81a5eb6a1d6e2331f9e"
}
